ocean_wave_tracing/__init__.py
ocean_wave_tracing/ocean_wave_tracing.py
ocean_wave_tracing/ray_metadata.json
ocean_wave_tracing/util_methods.py
ocean_wave_tracing/util_solvers.py
ocean_wave_tracing-1.0.3.dist-info/LICENSE
ocean_wave_tracing-1.0.3.dist-info/METADATA
ocean_wave_tracing-1.0.3.dist-info/WHEEL
ocean_wave_tracing-1.0.3.dist-info/entry_points.txt
ocean_wave_tracing-1.0.3.dist-info/RECORD
