Metadata-Version: 2.1
Name: ocean_wave_tracing
Version: 1.0.3
Summary: Ocean wave tracing
License: GPLv2
Author: Trygve Halsne
Author-email: trygveh@met.no
Requires-Python: >=3.8,<4.0
Classifier: License :: Other/Proprietary License
Classifier: Programming Language :: Python :: 3
Classifier: Programming Language :: Python :: 3.8
Classifier: Programming Language :: Python :: 3.9
Classifier: Programming Language :: Python :: 3.10
Classifier: Programming Language :: Python :: 3.11
Requires-Dist: cartopy (>=0.21)
Requires-Dist: cmocean (>=2.0)
Requires-Dist: matplotlib (>=3.5)
Requires-Dist: netCDF4 (>=1.6)
Requires-Dist: numpy (>=1.23)
Requires-Dist: pyproj (>=2.3)
Requires-Dist: scipy (>=1.9)
Requires-Dist: xarray (>=2022.6.0)
